GorillaTag/GorillaTag.py
GorillaTag/__init__.py
GorillaTag-0.3.dist-info/METADATA
GorillaTag-0.3.dist-info/WHEEL
GorillaTag-0.3.dist-info/top_level.txt
GorillaTag-0.3.dist-info/RECORD
