Metadata-Version: 2.1
Name: GorillaTag
Version: 0.3
Summary: A room tracker package
Author: Ace
Author-email: olimasterbiznes@gmail.com
Classifier: Programming Language :: Python :: 3
Classifier: License :: OSI Approved :: MIT License
Classifier: Operating System :: OS Independent
Requires-Python: >=3.6
Requires-Dist: requests
